seekerdemo/__init__.py
seekerdemo/demolicense.sio
seekerdemo/seekerdemo.cpython-311-linux.so
seekerdemo/seekerdemo.py
insideopt_demo-0.3.0.dist-info/AUTHORS.rst
insideopt_demo-0.3.0.dist-info/LICENSE.rst
insideopt_demo-0.3.0.dist-info/METADATA
insideopt_demo-0.3.0.dist-info/WHEEL
insideopt_demo-0.3.0.dist-info/top_level.txt
insideopt_demo-0.3.0.dist-info/RECORD
