Metadata-Version: 2.1
Name: insideopt-demo
Version: 0.3.0
Summary: InsideOpt Seeker Demo Distribution
Author: Meinolf Sellmann
Author-email: info@insideopt.com
Keywords: insideopt,seeker,demo,optimization
Classifier: Development Status :: 5 - Production/Stable
Classifier: Intended Audience :: Developers
Classifier: Natural Language :: English
Classifier: Programming Language :: Python :: 3.11
Classifier: Operating System :: POSIX :: Linux
Requires-Python: >=3.11.0
License-File: LICENSE.rst
License-File: AUTHORS.rst
